lsgm/__init__.py
lsgm/__main__.py
lsgm-0.0.1.dist-info/METADATA
lsgm-0.0.1.dist-info/WHEEL
lsgm-0.0.1.dist-info/licenses/license.md
lsgm-0.0.1.dist-info/RECORD
